MANIFEST.in
README.md
setup.py
Optimizer_with_theano/API.py
Optimizer_with_theano/Activation.py
Optimizer_with_theano/CapsNet.py
Optimizer_with_theano/CompileAndOptimize.py
Optimizer_with_theano/Conv.py
Optimizer_with_theano/Datasets.py
Optimizer_with_theano/Demo.py
Optimizer_with_theano/Dense.py
Optimizer_with_theano/Dropout.py
Optimizer_with_theano/Initializer.py
Optimizer_with_theano/Input.py
Optimizer_with_theano/Layer.py
Optimizer_with_theano/LayerInfo.py
Optimizer_with_theano/Loss.py
Optimizer_with_theano/Modify.py
Optimizer_with_theano/Optimizer.py
Optimizer_with_theano/Polynominal.py
Optimizer_with_theano/Pool.py
Optimizer_with_theano/RNN.py
Optimizer_with_theano/Util.py
Optimizer_with_theano/__init__.py
Optimizer_with_theano.egg-info/PKG-INFO
Optimizer_with_theano.egg-info/SOURCES.txt
Optimizer_with_theano.egg-info/dependency_links.txt
Optimizer_with_theano.egg-info/entry_points.txt
Optimizer_with_theano.egg-info/requires.txt
Optimizer_with_theano.egg-info/top_level.txt
Optimizer_with_theano/data_dir_for_optimizer/wine.csv
Optimizer_with_theano/data_dir_for_optimizer/mldata/mnist-original.mat
Optimizer_with_theano/sample/parakeet.jpg
Optimizer_with_theano/sample/psychedelic.jpg